{
  "id": 1,
  "name": "Mi ferreteria",
  "batch": 1,
  "amount": 1,
  "productList": [
    {
      "id": 1,
      "name": "Martillo",
      "stock": 10,
      "price": 4.0,
      "description": "El martillo es una herramienta de mano compuesta por una cabeza de metal, generalmente de acero, unida a un mango o mango de madera, plastico o fibra de vidrio. ",
      "regularPrice": 0.0,
      "discount": 0.0,
      "discountPercentage": 0.0
    },
    {
      "id": 2,
      "name": "Brocha",
      "stock": 10,
      "price": 2.0,
      "description": "La brocha es una herramienta de pintura vers치til y duradera, dise침ada para facilitar la aplicaci칩n uniforme de pintura sobre diversas superficies",
      "regularPrice": 0.0,
      "discount": 0.0,
      "discountPercentage": 0.0
    },
    {
      "id": 3,
      "name": "Clavo",
      "stock": 21,
      "price": 0.75,
      "description": "Los clavos son elementos de fijaci칩n fabricados en metal, generalmente acero, que se utilizan para unir y asegurar materiales de manera firme y duradera",
      "regularPrice": 0.0,
      "discount": 0.0,
      "discountPercentage": 0.0
    },
    {
      "id": 4,
      "name": "metro",
      "stock": 3,
      "price": 1.25,
      "description": "herramienta de medicion",
      "regularPrice": 0.0,
      "discount": 0.0,
      "discountPercentage": 50.0
    },
    {
      "id": 5,
      "name": "Taladro",
      "stock": 0,
      "price": 3.4,
      "description": "taladro multiusos",
      "regularPrice": 0.0,
      "discount": 0.0,
      "discountPercentage": 0.0
    }
  ],
  "cart": {
    "products": []
  }
}